punycodes/__init__.py
punycodes-1.0.1.data/scripts/punycodes
punycodes-1.0.1.dist-info/METADATA
punycodes-1.0.1.dist-info/WHEEL
punycodes-1.0.1.dist-info/top_level.txt
punycodes-1.0.1.dist-info/RECORD
