Metadata-Version: 2.1
Name: punycodes
Version: 1.0.1
Summary: IDNA codec
Home-page: http://pypi.python.org/pypi/punycodes/
Author: Philippe Grégoire
Author-email: git@pgregoire.xyz
License: LICENSE
Platform: UNKNOWN
